README.md
setup.py
spinnaker_python_client.egg-info/PKG-INFO
spinnaker_python_client.egg-info/SOURCES.txt
spinnaker_python_client.egg-info/dependency_links.txt
spinnaker_python_client.egg-info/requires.txt
spinnaker_python_client.egg-info/top_level.txt
swagger_client/__init__.py
swagger_client/api_client.py
swagger_client/configuration.py
swagger_client/rest.py
swagger_client/api/__init__.py
swagger_client/api/amazon_infrastructure_controller_api.py
swagger_client/api/application_controller_api.py
swagger_client/api/artifact_controller_api.py
swagger_client/api/auth_controller_api.py
swagger_client/api/bake_controller_api.py
swagger_client/api/build_controller_api.py
swagger_client/api/cluster_controller_api.py
swagger_client/api/concourse_controller_api.py
swagger_client/api/credentials_controller_api.py
swagger_client/api/ecs_server_group_events_controller_api.py
swagger_client/api/executions_controller_api.py
swagger_client/api/firewall_controller_api.py
swagger_client/api/image_controller_api.py
swagger_client/api/instance_controller_api.py
swagger_client/api/job_controller_api.py
swagger_client/api/load_balancer_controller_api.py
swagger_client/api/network_controller_api.py
swagger_client/api/pipeline_config_controller_api.py
swagger_client/api/pipeline_controller_api.py
swagger_client/api/pipeline_templates_controller_api.py
swagger_client/api/project_controller_api.py
swagger_client/api/pubsub_subscription_controller_api.py
swagger_client/api/reorder_pipelines_controller_api.py
swagger_client/api/search_controller_api.py
swagger_client/api/security_group_controller_api.py
swagger_client/api/server_group_controller_api.py
swagger_client/api/server_group_manager_controller_api.py
swagger_client/api/snapshot_controller_api.py
swagger_client/api/subnet_controller_api.py
swagger_client/api/task_controller_api.py
swagger_client/api/v_2_canary_controller_api.py
swagger_client/api/v_2_pipeline_templates_controller_api.py
swagger_client/api/version_controller_api.py
swagger_client/api/webhook_controller_api.py
swagger_client/models/__init__.py
swagger_client/models/account.py
swagger_client/models/account_details.py
swagger_client/models/granted_authority.py
