Metadata-Version: 1.0
Name: spinnaker-python-client
Version: 1.0.0
Summary: Spinnaker API
Home-page: UNKNOWN
Author: UNKNOWN
Author-email: UNKNOWN
License: UNKNOWN
Keywords: Swagger,Spinnaker API
Platform: UNKNOWN
